{
    "training_results": {
        "convergence_summary": [
            {
                "run": 1,
                "iteration": 4999,
                "loss": 0.41211897134780884,
                "v_mse": 0.0009304265258833766,
                "w_mse": 0.2749703526496887,
                "total_mse": 0.2759007791755721
            },
            {
                "run": 2,
                "iteration": 4999,
                "loss": 0.37913191318511963,
                "v_mse": 0.018897132948040962,
                "w_mse": 0.14652782678604126,
                "total_mse": 0.16542495973408222
            },
            {
                "run": 3,
                "iteration": 4999,
                "loss": 0.5146952271461487,
                "v_mse": 0.0424775704741478,
                "w_mse": 0.45696431398391724,
                "total_mse": 0.49944188445806503
            },
            {
                "run": 4,
                "iteration": 4999,
                "loss": 0.4958595633506775,
                "v_mse": 0.19191794097423553,
                "w_mse": 0.31509095430374146,
                "total_mse": 0.507008895277977
            },
            {
                "run": 5,
                "iteration": 4999,
                "loss": 0.3612378239631653,
                "v_mse": 0.015285955742001534,
                "w_mse": 0.6178048849105835,
                "total_mse": 0.633090840652585
            }
        ],
        "loss_progression": {
            "1": {
                "iterations": [
                    1,
                    251,
                    501,
                    751,
                    1001,
                    1251,
                    1501,
                    1751,
                    2001,
                    2251,
                    2501,
                    2751,
                    3001,
                    3251,
                    3501,
                    3751,
                    4001,
                    4251,
                    4501,
                    4751
                ],
                "losses": [
                    5.091195583343506,
                    4.718258380889893,
                    4.793496131896973,
                    3.2912943363189697,
                    0.8799377679824829,
                    0.6738228797912598,
                    0.6920086145401001,
                    0.5938505530357361,
                    0.680939793586731,
                    0.5677268505096436,
                    0.5449324250221252,
                    0.5248301029205322,
                    0.44304004311561584,
                    0.6044873595237732,
                    0.4971928894519806,
                    0.4493241310119629,
                    0.3773882985115051,
                    0.4097285270690918,
                    0.35473766922950745,
                    0.5745983719825745
                ]
            },
            "2": {
                "iterations": [
                    1,
                    251,
                    501,
                    751,
                    1001,
                    1251,
                    1501,
                    1751,
                    2001,
                    2251,
                    2501,
                    2751,
                    3001,
                    3251,
                    3501,
                    3751,
                    4001,
                    4251,
                    4501,
                    4751
                ],
                "losses": [
                    4.705129623413086,
                    4.425595283508301,
                    1.4788813591003418,
                    0.7419221997261047,
                    0.5256218314170837,
                    0.5537950992584229,
                    0.4543686807155609,
                    0.4347001016139984,
                    0.4436124563217163,
                    0.4471004605293274,
                    0.2683284282684326,
                    0.39600303769111633,
                    0.4160842001438141,
                    0.5068315863609314,
                    0.34567004442214966,
                    0.5100587010383606,
                    0.5127573013305664,
                    0.29072168469429016,
                    0.5318104028701782,
                    0.2741239368915558
                ]
            },
            "3": {
                "iterations": [
                    1,
                    251,
                    501,
                    751,
                    1001,
                    1251,
                    1501,
                    1751,
                    2001,
                    2251,
                    2501,
                    2751,
                    3001,
                    3251,
                    3501,
                    3751,
                    4001,
                    4251,
                    4501,
                    4751
                ],
                "losses": [
                    4.930665016174316,
                    4.772693634033203,
                    2.306067943572998,
                    0.8909130096435547,
                    0.6937029361724854,
                    0.4804931581020355,
                    0.5636157989501953,
                    0.5317968130111694,
                    0.5118434429168701,
                    0.4306959807872772,
                    0.4278470575809479,
                    0.38832077383995056,
                    0.5494657158851624,
                    0.4508364796638489,
                    0.37048786878585815,
                    0.4412594735622406,
                    0.4619990885257721,
                    0.44163641333580017,
                    0.32454997301101685,
                    0.5351811051368713
                ]
            },
            "4": {
                "iterations": [
                    1,
                    251,
                    501,
                    751,
                    1001,
                    1251,
                    1501,
                    1751,
                    2001,
                    2251,
                    2501,
                    2751,
                    3001,
                    3251,
                    3501,
                    3751,
                    4001,
                    4251,
                    4501,
                    4751
                ],
                "losses": [
                    5.091310977935791,
                    4.421388626098633,
                    4.4234724044799805,
                    4.166904449462891,
                    4.460465431213379,
                    4.224337100982666,
                    4.231012344360352,
                    3.9701507091522217,
                    3.787895917892456,
                    1.2268363237380981,
                    0.7065243124961853,
                    0.6556341648101807,
                    0.6165920495986938,
                    0.5452387928962708,
                    0.585159957408905,
                    0.6067436337471008,
                    0.5249782204627991,
                    0.4067504405975342,
                    0.4278740882873535,
                    0.48763442039489746
                ]
            },
            "5": {
                "iterations": [
                    1,
                    251,
                    501,
                    751,
                    1001,
                    1251,
                    1501,
                    1751,
                    2001,
                    2251,
                    2501,
                    2751,
                    3001,
                    3251,
                    3501,
                    3751,
                    4001,
                    4251,
                    4501,
                    4751
                ],
                "losses": [
                    4.823343753814697,
                    4.4478325843811035,
                    0.9603978395462036,
                    0.6165036559104919,
                    0.5634028315544128,
                    0.5500677227973938,
                    0.47576096653938293,
                    0.5188480019569397,
                    0.621739387512207,
                    0.4849131107330322,
                    0.3915126919746399,
                    0.48316138982772827,
                    0.43089884519577026,
                    0.46798962354660034,
                    0.4640028774738312,
                    0.5662454962730408,
                    0.4712440073490143,
                    0.37090373039245605,
                    0.435589998960495,
                    0.5645022392272949
                ]
            }
        },
        "statistics": {
            "total_mse_mean": 0.41617347185965625,
            "total_mse_std": 0.17016996927444314,
            "total_mse_cv": 40.88919183484827,
            "loss_mean": 0.43260869979858396,
            "loss_std": 0.061825993413889106,
            "loss_cv": 14.29143552653341,
            "best_run": 2,
            "best_total_mse": 0.16542495973408222,
            "best_v_mse": 0.018897132948040962,
            "best_w_mse": 0.14652782678604126,
            "success_rate": "5/5",
            "improvement": 60.25096001557074
        },
        "best_model": {
            "run": 2,
            "total_mse": 0.16542495973408222,
            "v_mse": 0.018897132948040962,
            "w_mse": 0.14652782678604126
        }
    },
    "analysis_info": {
        "total_runs": 5,
        "success_rate": "5/5",
        "improvement_over_mean": "60.3%",
        "stability_cv": "40.9%"
    }
}